laplace/__init__.py
laplace/base.py
laplace/client.py
laplace/collections.py
laplace/financials.py
laplace/funds.py
laplace/li.py
laplace/models.py
laplace/stocks.py
laplace_python_sdk-0.1.0.dist-info/licenses/LICENSE
laplace_python_sdk-0.1.0.dist-info/METADATA
laplace_python_sdk-0.1.0.dist-info/WHEEL
laplace_python_sdk-0.1.0.dist-info/top_level.txt
laplace_python_sdk-0.1.0.dist-info/RECORD
