Metadata-Version: 2.4
Name: laplace-python-sdk
Version: 0.1.0
Summary: Python SDK for Laplace stock data platform
Author: Laplace SDK Team
License: MIT
Project-URL: Homepage, https://laplace.finfree.co
Project-URL: Documentation, https://laplace.finfree.co/en/docs
Project-URL: Repository, https://github.com/Laplace-Analytics/laplace-python-sdk
Project-URL: Issues, https://github.com/Laplace-Analytics/laplace-python-sdk/issues
Keywords: stock,finance,api,sdk,laplace
Classifier: Development Status :: 4 - Beta
Classifier: Intended Audience :: Developers
Classifier: License :: OSI Approved :: MIT License
Classifier: Programming Language :: Python :: 3
Classifier: Programming Language :: Python :: 3.8
Classifier: Programming Language :: Python :: 3.9
Classifier: Programming Language :: Python :: 3.10
Classifier: Programming Language :: Python :: 3.11
Classifier: Programming Language :: Python :: 3.12
Classifier: Topic :: Office/Business :: Financial
Classifier: Topic :: Software Development :: Libraries :: Python Modules
Requires-Python: >=3.8
License-File: LICENSE
Requires-Dist: httpx>=0.24.0
Requires-Dist: pydantic>=2.0.0
Requires-Dist: typing-extensions>=4.0.0; python_version < "3.10"
Provides-Extra: dev
Requires-Dist: pytest>=7.0.0; extra == "dev"
Requires-Dist: pytest-asyncio>=0.21.0; extra == "dev"
Requires-Dist: black>=23.0.0; extra == "dev"
Requires-Dist: isort>=5.0.0; extra == "dev"
Requires-Dist: mypy>=1.0.0; extra == "dev"
Requires-Dist: ruff>=0.1.0; extra == "dev"
Dynamic: license-file
